mux2_1/mux2_1.v
/* mux _1 declaration
saved in  file hmux2_1.v */
module mux2_1(i1, i2, select, out);
    input i1, i2, select;
    output out;
    //wire select_inv;
    //wire a1_o, a2_o;
    //not n1(select_inv,select);
    //and a1(a1_o, a, select_inv);
    //and a1(a2_o, b, select);
    //or o1(out, a1_o, a2_o);
    assign out = i1 * !select + i2 * select;
endmodule

mux2_1/mux2_1_tb.v
/* Test bench for mux2_1.v 
is saved in file mux2_2_tb.v */
`include "mux2_1.v"

module mux2_1_tb;
    reg i1, i2, select;
    wire out;

    mux2_1 mux2_1_1(i1, i2, select, out);

    initial
        begin
            $dumpfile("mux2_1_tb.vcd");
            $dumpvars(0,mux2_1_tb);
            i1 = 0 ; i2 = 0; select = 0;
            #1
            i1 = 0 ; i2 = 0; select = 1;
            #1
            i1 = 0 ; i2 = 1; select = 0;
            #1
            i1 = 0 ; i2 = 1; select = 1;
            #1
            i1 = 1 ; i2 = 0; select = 0;
            #1
            i1 = 1 ; i2 = 0; select = 1;
            #1
            i1 = 1 ; i2 = 1; select = 0;
            #1
            i1 = 1 ; i2 = 1; select = 1;
        end

endmodule

mux2_1/mux2_1_tb.vcd
$date
	Sat Jul 27 23:58:38 2024
$end
$version
	Icarus Verilog
$end
$timescale
	1s
$end
$scope module mux2_1_tb $end
$var wire 1 ! out $end
$var reg 1 " i1 $end
$var reg 1 # i2 $end
$var reg 1 $ select $end
$scope module mux2_1_1 $end
$var wire 1 % i1 $end
$var wire 1 & i2 $end
$var wire 1 ! out $end
$var wire 1 ' select $end
$upscope $end
$upscope $end
$enddefinitions $end
#0
$dumpvars
0'
0&
0%
0$
0#
0"
0!
$end
#1
1$
1'
#2
0$
0'
1#
1&
0!
#3
1$
1'
1!
#4
0$
0'
0#
0&
1!
1"
1%
#5
1$
1'
0!
#6
0$
0'
1#
1&
1!
#7
1$
1'
1!
